elkoa/__init__.py
elkoa/gui/BatchLoad.ui
elkoa/gui/Convert.ui
elkoa/gui/ElkOpticsAnalyzer.py
elkoa/gui/FrameLayout.py
elkoa/gui/MainWindow.ui
elkoa/gui/ManipulateField.ui
elkoa/gui/SaveTab.ui
elkoa/gui/TensorElements.ui
elkoa/gui/UiDesigner.py
elkoa/gui/UiDialogs.py
elkoa/gui/UiMainWindow.py
elkoa/gui/Unit.ui
elkoa/gui/resources.qrc
elkoa/gui/resources_rc.py
elkoa/utils/__init__.py
elkoa/utils/convert.py
elkoa/utils/dicts.py
elkoa/utils/elk.py
elkoa/utils/io.py
elkoa/utils/misc.py
elkoa/utils/plot.py
elkoa-1.5.1.dist-info/AUTHORS
elkoa-1.5.1.dist-info/COPYING
elkoa-1.5.1.dist-info/LICENSE-3RD-PARTY
elkoa-1.5.1.dist-info/METADATA
elkoa-1.5.1.dist-info/WHEEL
elkoa-1.5.1.dist-info/entry_points.txt
elkoa-1.5.1.dist-info/pbr.json
elkoa-1.5.1.dist-info/top_level.txt
elkoa-1.5.1.dist-info/RECORD
