Metadata-Version: 2.1
Name: elkoa
Version: 1.5.1
Summary: plot and analyze Elk optics output data
Home-page: https://github.com/PandaScience/ElkOpticsAnalyzer
Author: René Wirnata
Author-email: rene.wirnata@pandascience.net
License: GPLv3+
Keywords: elk ab-initio simulation postprocessing optics analyze physics
Platform: UNKNOWN
Classifier: Development Status :: 5 - Production/Stable
Classifier: License :: OSI Approved :: GNU General Public License v3 or later (GPLv3+)
Classifier: Operating System :: OS Independent
Classifier: Programming Language :: Python :: 3 :: Only
Classifier: Environment :: Console
Classifier: Environment :: X11 Applications :: Qt
Classifier: Intended Audience :: Education
Classifier: Intended Audience :: Science/Research
Classifier: Natural Language :: English
Classifier: Operating System :: OS Independent
Classifier: Topic :: Scientific/Engineering :: Physics
Requires-Python: >=3
Requires-Dist: pip
Requires-Dist: pbr
Requires-Dist: setuptools
Requires-Dist: pyqt5
Requires-Dist: numpy
Requires-Dist: matplotlib
Requires-Dist: wrapt
Requires-Dist: numexpr
